grapejuice/__about__.py
grapejuice/__init__.py
grapejuice/__main__.py
grapejuice/background.py
grapejuice/tasks.py
grapejuice/gui/__init__.py
grapejuice/gui/about_window.py
grapejuice/gui/fast_flag_editor.py
grapejuice/gui/fast_flag_warning.py
grapejuice/gui/main_window.py
grapejuice/gui/yes_no_dialog.py
grapejuice_common/__init__.py
grapejuice_common/registry_file.py
grapejuice_common/registry_utils.py
grapejuice_common/robloxctrl.py
grapejuice_common/uninstall.py
grapejuice_common/update_info_providers.py
grapejuice_common/variables.py
grapejuice_common/winectrl.py
grapejuice_common/assets/disable_mime_assoc.reg
grapejuice_common/assets/roblox_documents_folder.reg
grapejuice_common/assets/desktop/grapejuice.desktop
grapejuice_common/assets/desktop/roblox-app.desktop
grapejuice_common/assets/desktop/roblox-player.desktop
grapejuice_common/assets/desktop/roblox-studio.desktop
grapejuice_common/assets/glade/about.glade
grapejuice_common/assets/glade/fast_flag_editor.glade
grapejuice_common/assets/glade/fast_flag_warning.glade
grapejuice_common/assets/glade/grapejuice.glade
grapejuice_common/assets/glade/grapejuice_components.glade
grapejuice_common/assets/icons/hicolor/128x128/apps/grapejuice-roblox-player.png
grapejuice_common/assets/icons/hicolor/128x128/apps/grapejuice-roblox-studio.png
grapejuice_common/assets/icons/hicolor/128x128/apps/grapejuice.png
grapejuice_common/assets/icons/hicolor/16x16/apps/grapejuice-roblox-player.png
grapejuice_common/assets/icons/hicolor/16x16/apps/grapejuice-roblox-studio.png
grapejuice_common/assets/icons/hicolor/16x16/apps/grapejuice.png
grapejuice_common/assets/icons/hicolor/24x24/apps/grapejuice-roblox-player.png
grapejuice_common/assets/icons/hicolor/24x24/apps/grapejuice-roblox-studio.png
grapejuice_common/assets/icons/hicolor/24x24/apps/grapejuice.png
grapejuice_common/assets/icons/hicolor/256x256/apps/grapejuice-roblox-player.png
grapejuice_common/assets/icons/hicolor/256x256/apps/grapejuice-roblox-studio.png
grapejuice-3.40.14.dist-info/LICENSE.md
grapejuice-3.40.14.dist-info/METADATA
grapejuice-3.40.14.dist-info/WHEEL
grapejuice-3.40.14.dist-info/entry_points.txt
grapejuice-3.40.14.dist-info/top_level.txt
grapejuice-3.40.14.dist-info/RECORD
