Metadata-Version: 2.1
Name: grapejuice
Version: 3.40.14
Summary: A simple wine+roblox management application
Home-page: https://gitlab.com/brinkervii/grapejuice
Author: BrinkerVII
Author-email: brinkervii@gmail.com
License: GPL-3
Keywords: grapejuice wine roblox studio
Platform: UNKNOWN
Classifier: Development Status :: 4 - Beta
Classifier: Programming Language :: Python :: 3.7
Requires-Python: >=3.7
License-File: LICENSE.md
Requires-Dist: psutil
Requires-Dist: pip
Requires-Dist: PyGObject
Requires-Dist: PyGObject-stubs
Requires-Dist: packaging
Requires-Dist: wheel
Requires-Dist: setuptools
Requires-Dist: requests
